[
  [
     {
       "categoryMainBannerUrl": "https://lbelchile.vtexassets.com/assets/vtex.file-manager-graphql/images/c4936264-90b5-4d4e-a87e-4b50b13f8322___cb5bd67766052062b966dcc282a7c50c.jpg",
       "categoryMainBannerUrlMobile": "https://lbelchile.vtexassets.com/assets/vtex.file-manager-graphql/images/86d0be43-f967-44ab-bb93-9f89585238cf___b067a4a892d30f2eb6cdf5582adba66a.jpg",
       "categoryNewUrlMTO": "maquillaje?utmi_cp=Isabellstore"
     }
  ],
  [
     {
       "categoryBtnMoreText": "Mostrar m치s"
     }
  ],
  [
     {
       "categoryOrderTitle": "Ordenar por Relevancia",
       "categoryOrderTitleMobile": "Relevancia",
       "categoryFirstOption": "Relevancia"
     }
  ],
  [
    {
      "categoryOrderIndex": "0",
      "categoryOrderOptions": "Ventas",
      "categoryOrderUrlVentas": "?order=OrderByTopSaleDESC"
    },
    {
      "categoryOrderIndex": "1",
      "categoryOrderOptions": "M치s reciente",
      "categoryOrderUrlReciente": "?order=OrderByReleaseDateDESC"
    },
    {
      "categoryOrderIndex": "2",
      "categoryOrderOptions": "Descuento"
    },
    {
      "categoryOrderIndex": "3",
      "categoryOrderOptions": "Precios m치s alto"
    },
    {
      "categoryOrderIndex": "4",
      "categoryOrderOptions": "Precios m치s bajo",
      "categoryOrderUrlLowPrices": "?order=OrderByPriceASC"
    }
  ]
]